pymusickit/__init__.py
pymusickit/key_finder.py
pymusickit/keyfinder.py
pymusickit/music_theory.py
pymusickit/scales.py
pymusickit/music_theory/__init__.py
pymusickit/music_theory/relation.py
pymusickit/music_theory/scales.py
pymusickit-0.1.1.dist-info/METADATA
pymusickit-0.1.1.dist-info/WHEEL
pymusickit-0.1.1.dist-info/entry_points.txt
pymusickit-0.1.1.dist-info/top_level.txt
pymusickit-0.1.1.dist-info/RECORD
