Metadata-Version: 2.1
Name: pymusickit
Version: 0.1.1
Summary: A Python package for music analysis.  Keyfinder Forked from "https://github.com/jackmcarthur/musical-key-finder"
Home-page: https://github.com/bin2ai/pymusickit
Author: bin2ai
Classifier: Development Status :: 3 - Alpha
Classifier: Intended Audience :: Developers
Classifier: License :: OSI Approved :: MIT License
Classifier: Programming Language :: Python :: 3
Classifier: Programming Language :: Python :: 3.6
Classifier: Programming Language :: Python :: 3.7
Classifier: Programming Language :: Python :: 3.8
Classifier: Programming Language :: Python :: 3.9
Classifier: Programming Language :: Python :: 3.10
Classifier: Operating System :: OS Independent
Requires-Python: >=3.6
